[
	{
		"customer_id" : 1,
		"FirstName" : "Gustavo",
		"LastName" : "Achong",
		"EmailAddress" : "gustavo0@adventure-works.com",
		"City" : "Seattle",
		"state_province" : "Washington",
		"country_region" : "United States"
	},
	{
		"customer_id" : 2,
		"FirstName" : "Catherine",
		"LastName" : "Abel",
		"EmailAddress" : "catherine0@adventure-works.com",
		"City" : "Renton",
		"state_province" : "Washington",
		"country_region" : "United States"
	},
	{
		"customer_id" : 2,
		"FirstName" : "Catherine",
		"LastName" : "Abel",
		"EmailAddress" : "catherine0@adventure-works.com",
		"City" : "Renton",
		"state_province" : "Washington",
		"country_region" : "United States"
	},
	{
		"customer_id" : 3,
		"FirstName" : "Kim",
		"LastName" : "Abercrombie",
		"EmailAddress" : "kim2@adventure-works.com",
		"City" : "Irving",
		"state_province" : "Texas",
		"country_region" : "United States"
	},
	{
		"customer_id" : 4,
		"FirstName" : "Humberto",
		"LastName" : "Acevedo",
		"EmailAddress" : "humberto0@adventure-works.com",
		"City" : "Austin",
		"state_province" : "Texas",
		"country_region" : "United States"
	},
	{
		"customer_id" : 4,
		"FirstName" : "Humberto",
		"LastName" : "Acevedo",
		"EmailAddress" : "humberto0@adventure-works.com",
		"City" : "Austin",
		"state_province" : "Texas",
		"country_region" : "United States"
	},
	{
		"customer_id" : 5,
		"FirstName" : "Pilar",
		"LastName" : "Ackerman",
		"EmailAddress" : "pilar1@adventure-works.com",
		"City" : "Fremont",
		"state_province" : "California",
		"country_region" : "United States"
	},
	{
		"customer_id" : 6,
		"FirstName" : "Frances",
		"LastName" : "Adams",
		"EmailAddress" : "frances0@adventure-works.com",
		"City" : "Camarillo",
		"state_province" : "California",
		"country_region" : "United States"
	},
	{
		"customer_id" : 7,
		"FirstName" : "Margaret",
		"LastName" : "Smith",
		"EmailAddress" : "margaret0@adventure-works.com",
		"City" : "Salt Lake City",
		"state_province" : "Utah",
		"country_region" : "United States"
	},
	{
		"customer_id" : 8,
		"FirstName" : "Carla",
		"LastName" : "Adams",
		"EmailAddress" : "carla0@adventure-works.com",
		"City" : "Miami",
		"state_province" : "Florida",
		"country_region" : "United States"
	},
	{
		"customer_id" : 9,
		"FirstName" : "Jay",
		"LastName" : "Adams",
		"EmailAddress" : "jay1@adventure-works.com",
		"City" : "Millington",
		"state_province" : "Tennessee",
		"country_region" : "United States"
	},
	{
		"customer_id" : 10,
		"FirstName" : "Ronald",
		"LastName" : "Adina",
		"EmailAddress" : "ronald0@adventure-works.com",
		"City" : "Burnaby",
		"state_province" : "British Columbia",
		"country_region" : "Canada"
	},
	{
		"customer_id" : 11,
		"FirstName" : "Samuel",
		"LastName" : "Agcaoili",
		"EmailAddress" : "samuel0@adventure-works.com",
		"City" : "Toronto",
		"state_province" : "Ontario",
		"country_region" : "Canada"
	},
	{
		"customer_id" : 12,
		"FirstName" : "James",
		"LastName" : "Aguilar",
		"EmailAddress" : "james2@adventure-works.com",
		"City" : "Toronto",
		"state_province" : "Ontario",
		"country_region" : "Canada"
	},
	{
		"customer_id" : 13,
		"FirstName" : "Robert",
		"LastName" : "Ahlering",
		"EmailAddress" : "robert1@adventure-works.com",
		"City" : "Les Ulis",
		"state_province" : "Essonne",
		"country_region" : "France"
	},
	{
		"customer_id" : 14,
		"FirstName" : "François",
		"LastName" : "Ferrier",
		"EmailAddress" : "françois1@adventure-works.com",
		"City" : "Frankfurt am Main",
		"state_province" : "Saarland",
		"country_region" : "Germany"
	},
	{
		"customer_id" : 15,
		"FirstName" : "Kim",
		"LastName" : "Akers",
		"EmailAddress" : "kim3@adventure-works.com",
		"City" : "Lavender Bay",
		"state_province" : "New South Wales",
		"country_region" : "Australia"
	},
	{
		"customer_id" : 16,
		"FirstName" : "Lili",
		"LastName" : "Alameda",
		"EmailAddress" : "lili0@adventure-works.com",
		"City" : "London",
		"state_province" : "England",
		"country_region" : "United Kingdom"
	},
	{
		"customer_id" : 17,
		"FirstName" : "Amy",
		"LastName" : "Alberts",
		"EmailAddress" : "amy1@adventure-works.com",
		"City" : "Newport News",
		"state_province" : "Virginia",
		"country_region" : "United States"
	},
	{
		"customer_id" : 18,
		"FirstName" : "Anna",
		"LastName" : "Albright",
		"EmailAddress" : "anna0@adventure-works.com",
		"City" : "Zeeland",
		"state_province" : "Michigan",
		"country_region" : "United States"
	},
	{
		"customer_id" : 19,
		"FirstName" : "Milton",
		"LastName" : "Albury",
		"EmailAddress" : "milton0@adventure-works.com",
		"City" : "Bothell",
		"state_province" : "Washington",
		"country_region" : "United States"
	},
	{
		"customer_id" : 19,
		"FirstName" : "Milton",
		"LastName" : "Albury",
		"EmailAddress" : "milton0@adventure-works.com",
		"City" : "Bothell",
		"state_province" : "Washington",
		"country_region" : "United States"
	},
	{
		"customer_id" : 20,
		"FirstName" : "Paul",
		"LastName" : "Alcorn",
		"EmailAddress" : "paul2@adventure-works.com",
		"City" : "Kent",
		"state_province" : "Washington",
		"country_region" : "United States"
	},
	{
		"customer_id" : 21,
		"FirstName" : "Gregory",
		"LastName" : "Alderson",
		"EmailAddress" : "gregory0@adventure-works.com",
		"City" : "Irving",
		"state_province" : "Texas",
		"country_region" : "United States"
	},
	{
		"customer_id" : 22,
		"FirstName" : "J. Phillip",
		"LastName" : "Alexander",
		"EmailAddress" : "jphillip0@adventure-works.com",
		"City" : "North Sioux City",
		"state_province" : "South Dakota",
		"country_region" : "United States"
	},
	{
		"customer_id" : 23,
		"FirstName" : "Michelle",
		"LastName" : "Alexander",
		"EmailAddress" : "michelle0@adventure-works.com",
		"City" : "San Ramon",
		"state_province" : "California",
		"country_region" : "United States"
	},
	{
		"customer_id" : 24,
		"FirstName" : "Sean",
		"LastName" : "Jacobson",
		"EmailAddress" : "sean2@adventure-works.com",
		"City" : "Union City",
		"state_province" : "California",
		"country_region" : "United States"
	},
	{
		"customer_id" : 25,
		"FirstName" : "Phyllis",
		"LastName" : "Allen",
		"EmailAddress" : "phyllis0@adventure-works.com",
		"City" : "El Segundo",
		"state_province" : "California",
		"country_region" : "United States"
	},
	{
		"customer_id" : 26,
		"FirstName" : "Marvin",
		"LastName" : "Allen",
		"EmailAddress" : "marvin0@adventure-works.com",
		"City" : "Miami",
		"state_province" : "Florida",
		"country_region" : "United States"
	},
	{
		"customer_id" : 27,
		"FirstName" : "Michael",
		"LastName" : "Allen",
		"EmailAddress" : "michael10@adventure-works.com",
		"City" : "Millington",
		"state_province" : "Tennessee",
		"country_region" : "United States"
	},
	{
		"customer_id" : 28,
		"FirstName" : "Cecil",
		"LastName" : "Allison",
		"EmailAddress" : "cecil0@adventure-works.com",
		"City" : "Toronto",
		"state_province" : "Ontario",
		"country_region" : "Canada"
	},
	{
		"customer_id" : 29,
		"FirstName" : "Oscar",
		"LastName" : "Alpuerto",
		"EmailAddress" : "oscar0@adventure-works.com",
		"City" : "Chalk Riber",
		"state_province" : "Ontario",
		"country_region" : "Canada"
	},
	{
		"customer_id" : 30,
		"FirstName" : "Sandra",
		"LastName" : "Altamirano",
		"EmailAddress" : "sandra1@adventure-works.com",
		"City" : "Quebec",
		"state_province" : "Quebec",
		"country_region" : "Canada"
	},
	{
		"customer_id" : 31,
		"FirstName" : "Selena",
		"LastName" : "Alvarado",
		"EmailAddress" : "selena0@adventure-works.com",
		"City" : "Paris",
		"state_province" : "Seine (Paris)",
		"country_region" : "France"
	},
	{
		"customer_id" : 32,
		"FirstName" : "Emilio",
		"LastName" : "Alvaro",
		"EmailAddress" : "emilio0@adventure-works.com",
		"City" : "Stuttgart",
		"state_province" : "Saarland",
		"country_region" : "Germany"
	},
	{
		"customer_id" : 33,
		"FirstName" : "Maxwell",
		"LastName" : "Amland",
		"EmailAddress" : "maxwell0@adventure-works.com",
		"City" : "Lavender Bay",
		"state_province" : "New South Wales",
		"country_region" : "Australia"
	},
	{
		"customer_id" : 34,
		"FirstName" : "Mae",
		"LastName" : "Anderson",
		"EmailAddress" : "mae0@adventure-works.com",
		"City" : "Warrington",
		"state_province" : "England",
		"country_region" : "United Kingdom"
	},
	{
		"customer_id" : 35,
		"FirstName" : "Ramona",
		"LastName" : "Antrim",
		"EmailAddress" : "ramona0@adventure-works.com",
		"City" : "West Kingston",
		"state_province" : "Rhode Island",
		"country_region" : "United States"
	},
	{
		"customer_id" : 36,
		"FirstName" : "Sabria",
		"LastName" : "Appelbaum",
		"EmailAddress" : "sabria0@adventure-works.com",
		"City" : "South Bend",
		"state_province" : "Indiana",
		"country_region" : "United States"
	},
	{
		"customer_id" : 37,
		"FirstName" : "Hannah",
		"LastName" : "Arakawa",
		"EmailAddress" : "hannah0@adventure-works.com",
		"City" : "Puyallup",
		"state_province" : "Washington",
		"country_region" : "United States"
	},
	{
		"customer_id" : 38,
		"FirstName" : "Kyley",
		"LastName" : "Arbelaez",
		"EmailAddress" : "kyley0@adventure-works.com",
		"City" : "Billings",
		"state_province" : "Montana",
		"country_region" : "United States"
	},
	{
		"customer_id" : 39,
		"FirstName" : "Tom",
		"LastName" : "Johnston",
		"EmailAddress" : "tom1@adventure-works.com",
		"City" : "Edina",
		"state_province" : "Minnesota",
		"country_region" : "United States"
	},
	{
		"customer_id" : 40,
		"FirstName" : "Thomas",
		"LastName" : "Armstrong",
		"EmailAddress" : "thomas1@adventure-works.com",
		"City" : "Laredo",
		"state_province" : "Texas",
		"country_region" : "United States"
	},
	{
		"customer_id" : 41,
		"FirstName" : "John",
		"LastName" : "Arthur",
		"EmailAddress" : "john6@adventure-works.com",
		"City" : "Milpitas",
		"state_province" : "California",
		"country_region" : "United States"
	},
	{
		"customer_id" : 42,
		"FirstName" : "Chris",
		"LastName" : "Ashton",
		"EmailAddress" : "chris3@adventure-works.com",
		"City" : "Newport Beach",
		"state_province" : "California",
		"country_region" : "United States"
	},
	{
		"customer_id" : 43,
		"FirstName" : "Teresa",
		"LastName" : "Atkinson",
		"EmailAddress" : "teresa0@adventure-works.com",
		"City" : "Salt Lake City",
		"state_province" : "Utah",
		"country_region" : "United States"
	},
	{
		"customer_id" : 44,
		"FirstName" : "John",
		"LastName" : "Ault",
		"EmailAddress" : "john7@adventure-works.com",
		"City" : "Huntsville",
		"state_province" : "Alabama",
		"country_region" : "United States"
	},
	{
		"customer_id" : 45,
		"FirstName" : "Robert",
		"LastName" : "Avalos",
		"EmailAddress" : "robert2@adventure-works.com",
		"City" : "La Vergne",
		"state_province" : "Tennessee",
		"country_region" : "United States"
	},
	{
		"customer_id" : 46,
		"FirstName" : "Stephen",
		"LastName" : "Ayers",
		"EmailAddress" : "stephen1@adventure-works.com",
		"City" : "Calgary",
		"state_province" : "Alberta",
		"country_region" : "Canada"
	},
	{
		"customer_id" : 47,
		"FirstName" : "Phillip",
		"LastName" : "Bacalzo",
		"EmailAddress" : "phillip0@adventure-works.com",
		"City" : "Toronto",
		"state_province" : "Ontario",
		"country_region" : "Canada"
	},
	{
		"customer_id" : 48,
		"FirstName" : "Daniel",
		"LastName" : "Blanco",
		"EmailAddress" : "daniel0@adventure-works.com",
		"City" : "Montreal",
		"state_province" : "Quebec",
		"country_region" : "Canada"
	},
	{
		"customer_id" : 49,
		"FirstName" : "Cory",
		"LastName" : "Booth",
		"EmailAddress" : "cory0@adventure-works.com",
		"City" : "Roncq",
		"state_province" : "Nord",
		"country_region" : "France"
	},
	{
		"customer_id" : 50,
		"FirstName" : "James",
		"LastName" : "Bailey",
		"EmailAddress" : "james3@adventure-works.com",
		"City" : "Berlin",
		"state_province" : "Brandenburg",
		"country_region" : "Germany"
	},
	{
		"customer_id" : 51,
		"FirstName" : "Douglas",
		"LastName" : "Baldwin",
		"EmailAddress" : "douglas1@adventure-works.com",
		"City" : "Cloverdale",
		"state_province" : "South Australia",
		"country_region" : "Australia"
	},
	{
		"customer_id" : 52,
		"FirstName" : "Jennifer",
		"LastName" : "Bales",
		"EmailAddress" : "jennifer0@adventure-works.com",
		"City" : "Gloucestershire",
		"state_province" : "England",
		"country_region" : "United Kingdom"
	},
	{
		"customer_id" : 53,
		"FirstName" : "Alberto",
		"LastName" : "Baltazar",
		"EmailAddress" : "alberto0@adventure-works.com",
		"City" : "Norwood",
		"state_province" : "Massachusetts",
		"country_region" : "United States"
	},
	{
		"customer_id" : 54,
		"FirstName" : "Wayne",
		"LastName" : "Banack",
		"EmailAddress" : "wayne0@adventure-works.com",
		"City" : "Melville",
		"state_province" : "New York",
		"country_region" : "United States"
	},
	{
		"customer_id" : 55,
		"FirstName" : "Darrell",
		"LastName" : "Banks",
		"EmailAddress" : "darrell0@adventure-works.com",
		"City" : "Medford",
		"state_province" : "Oregon",
		"country_region" : "United States"
	},
	{
		"customer_id" : 56,
		"FirstName" : "Angela",
		"LastName" : "Barbariol",
		"EmailAddress" : "angela1@adventure-works.com",
		"City" : "Portland",
		"state_province" : "Oregon",
		"country_region" : "United States"
	},
	{
		"customer_id" : 57,
		"FirstName" : "David",
		"LastName" : "Barber",
		"EmailAddress" : "david9@adventure-works.com",
		"City" : "West Chicago",
		"state_province" : "Illinois",
		"country_region" : "United States"
	},
	{
		"customer_id" : 58,
		"FirstName" : "Robert",
		"LastName" : "Barker",
		"EmailAddress" : "robert3@adventure-works.com",
		"City" : "Chicago",
		"state_province" : "Illinois",
		"country_region" : "United States"
	},
	{
		"customer_id" : 59,
		"FirstName" : "Rebecca",
		"LastName" : "Barley",
		"EmailAddress" : "rebecca1@adventure-works.com",
		"City" : "Visalia",
		"state_province" : "California",
		"country_region" : "United States"
	},
	{
		"customer_id" : 60,
		"FirstName" : "Brenda",
		"LastName" : "Barlow",
		"EmailAddress" : "brenda1@adventure-works.com",
		"City" : "Hayward",
		"state_province" : "California",
		"country_region" : "United States"
	},
	{
		"customer_id" : 61,
		"FirstName" : "Josh",
		"LastName" : "Barnhill",
		"EmailAddress" : "josh0@adventure-works.com",
		"City" : "Fullerton",
		"state_province" : "California",
		"country_region" : "United States"
	},
	{
		"customer_id" : 62,
		"FirstName" : "Adam",
		"LastName" : "Barr",
		"EmailAddress" : "adam0@adventure-works.com",
		"City" : "Nashville",
		"state_province" : "Tennessee",
		"country_region" : "United States"
	},
	{
		"customer_id" : 63,
		"FirstName" : "Norma",
		"LastName" : "Barrera",
		"EmailAddress" : "norma0@adventure-works.com",
		"City" : "Greensboro",
		"state_province" : "North Carolina",
		"country_region" : "United States"
	},
	{
		"customer_id" : 64,
		"FirstName" : "Gytis",
		"LastName" : "Barzdukas",
		"EmailAddress" : "gytis0@adventure-works.com",
		"City" : "Toronto",
		"state_province" : "Ontario",
		"country_region" : "Canada"
	},
	{
		"customer_id" : 65,
		"FirstName" : "David",
		"LastName" : "Bartness",
		"EmailAddress" : "david10@adventure-works.com",
		"City" : "Weston",
		"state_province" : "Ontario",
		"country_region" : "Canada"
	},
	{
		"customer_id" : 66,
		"FirstName" : "Karel",
		"LastName" : "Bates",
		"EmailAddress" : "karel0@adventure-works.com",
		"City" : "Burnaby",
		"state_province" : "British Columbia",
		"country_region" : "Canada"
	},
	{
		"customer_id" : 67,
		"FirstName" : "Ciro",
		"LastName" : "Bauer",
		"EmailAddress" : "ciro0@adventure-works.com",
		"City" : "Verrieres Le Buisson",
		"state_province" : "Essonne",
		"country_region" : "France"
	},
	{
		"customer_id" : 68,
		"FirstName" : "Glenna",
		"LastName" : "Beanston",
		"EmailAddress" : "glenna0@adventure-works.com",
		"City" : "Muehlheim",
		"state_province" : "Hamburg",
		"country_region" : "Germany"
	},
	{
		"customer_id" : 69,
		"FirstName" : "Shaun",
		"LastName" : "Beasley",
		"EmailAddress" : "shaun0@adventure-works.com",
		"City" : "Lavender Bay",
		"state_province" : "New South Wales",
		"country_region" : "Australia"
	},
	{
		"customer_id" : 70,
		"FirstName" : "John",
		"LastName" : "Beaver",
		"EmailAddress" : "john8@adventure-works.com",
		"City" : "London",
		"state_province" : "England",
		"country_region" : "United Kingdom"
	},
	{
		"customer_id" : 71,
		"FirstName" : "Christopher",
		"LastName" : "Beck",
		"EmailAddress" : "christopher1@adventure-works.com",
		"City" : "Farmington",
		"state_province" : "Connecticut",
		"country_region" : "United States"
	},
	{
		"customer_id" : 72,
		"FirstName" : "Bradley",
		"LastName" : "Beck",
		"EmailAddress" : "bradley0@adventure-works.com",
		"City" : "Nashua",
		"state_province" : "New Hampshire",
		"country_region" : "United States"
	},
	{
		"customer_id" : 73,
		"FirstName" : "Benjamin",
		"LastName" : "Becker",
		"EmailAddress" : "benjamin1@adventure-works.com",
		"City" : "North Bend",
		"state_province" : "Washington",
		"country_region" : "United States"
	},
	{
		"customer_id" : 74,
		"FirstName" : "Ann",
		"LastName" : "Beebe",
		"EmailAddress" : "ann0@adventure-works.com",
		"City" : "Portland",
		"state_province" : "Oregon",
		"country_region" : "United States"
	},
	{
		"customer_id" : 75,
		"FirstName" : "Shane",
		"LastName" : "Belli",
		"EmailAddress" : "shane1@adventure-works.com",
		"City" : "Garland",
		"state_province" : "Texas",
		"country_region" : "United States"
	},
	{
		"customer_id" : 76,
		"FirstName" : "Stanley",
		"LastName" : "Alan",
		"EmailAddress" : "stanley0@adventure-works.com",
		"City" : "Wood Dale",
		"state_province" : "Illinois",
		"country_region" : "United States"
	},
	{
		"customer_id" : 77,
		"FirstName" : "Mason",
		"LastName" : "Bendixen",
		"EmailAddress" : "mason0@adventure-works.com",
		"City" : "San Diego",
		"state_province" : "California",
		"country_region" : "United States"
	},
	{
		"customer_id" : 78,
		"FirstName" : "John",
		"LastName" : "Bennetts",
		"EmailAddress" : "john9@adventure-works.com",
		"City" : "Ontario",
		"state_province" : "California",
		"country_region" : "United States"
	},
	{
		"customer_id" : 79,
		"FirstName" : "Ido",
		"LastName" : "Ben-Sachar",
		"EmailAddress" : "ido0@adventure-works.com",
		"City" : "Greeley",
		"state_province" : "Colorado",
		"country_region" : "United States"
	},
	{
		"customer_id" : 80,
		"FirstName" : "Edna",
		"LastName" : "Benson",
		"EmailAddress" : "edna0@adventure-works.com",
		"City" : "Sunrise",
		"state_province" : "Florida",
		"country_region" : "United States"
	},
	{
		"customer_id" : 81,
		"FirstName" : "Payton",
		"LastName" : "Benson",
		"EmailAddress" : "payton0@adventure-works.com",
		"City" : "Miami",
		"state_province" : "Florida",
		"country_region" : "United States"
	},
	{
		"customer_id" : 82,
		"FirstName" : "Max",
		"LastName" : "Benson",
		"EmailAddress" : "max0@adventure-works.com",
		"City" : "Vancouver",
		"state_province" : "British Columbia",
		"country_region" : "Canada"
	},
	{
		"customer_id" : 83,
		"FirstName" : "Scot",
		"LastName" : "Bent",
		"EmailAddress" : "scot0@adventure-works.com",
		"City" : "Ottawa",
		"state_province" : "Ontario",
		"country_region" : "Canada"
	},
	{
		"customer_id" : 84,
		"FirstName" : "Richard",
		"LastName" : "Bentley",
		"EmailAddress" : "richard0@adventure-works.com",
		"City" : "Etobicoke",
		"state_province" : "Ontario",
		"country_region" : "Canada"
	},
	{
		"customer_id" : 85,
		"FirstName" : "Marian",
		"LastName" : "Berch",
		"EmailAddress" : "marian0@adventure-works.com",
		"City" : "Courbevoie",
		"state_province" : "Hauts de Seine",
		"country_region" : "France"
	},
	{
		"customer_id" : 86,
		"FirstName" : "Karen",
		"LastName" : "Berge",
		"EmailAddress" : "karen2@adventure-works.com",
		"City" : "Essen",
		"state_province" : "Hamburg",
		"country_region" : "Germany"
	},
	{
		"customer_id" : 87,
		"FirstName" : "Alexander",
		"LastName" : "Berger",
		"EmailAddress" : "alexander0@adventure-works.com",
		"City" : "Lane Cove",
		"state_province" : "New South Wales",
		"country_region" : "Australia"
	},
	{
		"customer_id" : 88,
		"FirstName" : "John",
		"LastName" : "Berger",
		"EmailAddress" : "john10@adventure-works.com",
		"City" : "Milton Keynes",
		"state_province" : "England",
		"country_region" : "United Kingdom"
	},
	{
		"customer_id" : 89,
		"FirstName" : "Kris",
		"LastName" : "Bergin",
		"EmailAddress" : "kris0@adventure-works.com",
		"City" : "Oberlin",
		"state_province" : "Ohio",
		"country_region" : "United States"
	},
	{
		"customer_id" : 90,
		"FirstName" : "Andreas",
		"LastName" : "Berglund",
		"EmailAddress" : "andreas1@adventure-works.com",
		"City" : "Chantilly",
		"state_province" : "Virginia",
		"country_region" : "United States"
	},
	{
		"customer_id" : 91,
		"FirstName" : "Robert",
		"LastName" : "Bernacchi",
		"EmailAddress" : "robert4@adventure-works.com",
		"City" : "Beaverton",
		"state_province" : "Oregon",
		"country_region" : "United States"
	},
	{
		"customer_id" : 92,
		"FirstName" : "Matthias",
		"LastName" : "Berndt",
		"EmailAddress" : "matthias1@adventure-works.com",
		"City" : "Woodinville",
		"state_province" : "Washington",
		"country_region" : "United States"
	},
	{
		"customer_id" : 93,
		"FirstName" : "John",
		"LastName" : "Berry",
		"EmailAddress" : "john11@adventure-works.com",
		"City" : "Round Rock",
		"state_province" : "Texas",
		"country_region" : "United States"
	},
	{
		"customer_id" : 94,
		"FirstName" : "Steven",
		"LastName" : "Brown",
		"EmailAddress" : "steven1@adventure-works.com",
		"City" : "Fort Worth",
		"state_province" : "Texas",
		"country_region" : "United States"
	},
	{
		"customer_id" : 95,
		"FirstName" : "Chris",
		"LastName" : "Bidelman",
		"EmailAddress" : "chris4@adventure-works.com",
		"City" : "Pleasanton",
		"state_province" : "California",
		"country_region" : "United States"
	},
	{
		"customer_id" : 96,
		"FirstName" : "Mary",
		"LastName" : "Billstrom",
		"EmailAddress" : "mary3@adventure-works.com",
		"City" : "Santa Ana",
		"state_province" : "California",
		"country_region" : "United States"
	},
	{
		"customer_id" : 97,
		"FirstName" : "Jimmy",
		"LastName" : "Bischoff",
		"EmailAddress" : "jimmy1@adventure-works.com",
		"City" : "Newark",
		"state_province" : "California",
		"country_region" : "United States"
	},
	{
		"customer_id" : 98,
		"FirstName" : "Mary",
		"LastName" : "Bishop",
		"EmailAddress" : "mary4@adventure-works.com",
		"City" : "Miami",
		"state_province" : "Florida",
		"country_region" : "United States"
	},
	{
		"customer_id" : 99,
		"FirstName" : "Mae",
		"LastName" : "Black",
		"EmailAddress" : "mae1@adventure-works.com",
		"City" : "Sarasota",
		"state_province" : "Florida",
		"country_region" : "United States"
	},
	{
		"customer_id" : 100,
		"FirstName" : "Jackie",
		"LastName" : "Blackwell",
		"EmailAddress" : "jackie0@adventure-works.com",
		"City" : "Markham",
		"state_province" : "Ontario",
		"country_region" : "Canada"
	},
	{
		"customer_id" : 101,
		"FirstName" : "Donald",
		"LastName" : "Blanton",
		"EmailAddress" : "donald0@adventure-works.com",
		"City" : "Toronto",
		"state_province" : "Ontario",
		"country_region" : "Canada"
	},
	{
		"customer_id" : 102,
		"FirstName" : "Linda",
		"LastName" : "Burnett",
		"EmailAddress" : "linda4@adventure-works.com",
		"City" : "Toronto",
		"state_province" : "Ontario",
		"country_region" : "Canada"
	},
	{
		"customer_id" : 103,
		"FirstName" : "Michael",
		"LastName" : "Blythe",
		"EmailAddress" : "michael11@adventure-works.com",
		"City" : "Pantin",
		"state_province" : "Seine Saint Denis",
		"country_region" : "France"
	},
	{
		"customer_id" : 104,
		"FirstName" : "Gabriel",
		"LastName" : "Bockenkamp",
		"EmailAddress" : "gabriel0@adventure-works.com",
		"City" : "Duesseldorf",
		"state_province" : "Hessen",
		"country_region" : "Germany"
	},
	{
		"customer_id" : 105,
		"FirstName" : "Michael",
		"LastName" : "Bohling",
		"EmailAddress" : "michael12@adventure-works.com",
		"City" : "Alexandria",
		"state_province" : "New South Wales",
		"country_region" : "Australia"
	},
	{
		"customer_id" : 106,
		"FirstName" : "Corinna",
		"LastName" : "Bolender",
		"EmailAddress" : "corinna0@adventure-works.com",
		"City" : "Wokingham",
		"state_province" : "England",
		"country_region" : "United Kingdom"
	},
	{
		"customer_id" : 107,
		"FirstName" : "Luis",
		"LastName" : "Bonifaz",
		"EmailAddress" : "luis0@adventure-works.com",
		"City" : "Randolph",
		"state_province" : "Massachusetts",
		"country_region" : "United States"
	},
	{
		"customer_id" : 108,
		"FirstName" : "Randall",
		"LastName" : "Boseman",
		"EmailAddress" : "randall0@adventure-works.com",
		"City" : "Kittery",
		"state_province" : "Maine",
		"country_region" : "United States"
	},
	{
		"customer_id" : 109,
		"FirstName" : "Stephanie",
		"LastName" : "Bourne",
		"EmailAddress" : "stephanie1@adventure-works.com",
		"City" : "Issaquah",
		"state_province" : "Washington",
		"country_region" : "United States"
	},
	{
		"customer_id" : 110,
		"FirstName" : "Eli",
		"LastName" : "Bowen",
		"EmailAddress" : "eli0@adventure-works.com",
		"City" : "Idaho Falls",
		"state_province" : "Idaho",
		"country_region" : "United States"
	},
	{
		"customer_id" : 111,
		"FirstName" : "Lester",
		"LastName" : "Bowman",
		"EmailAddress" : "lester0@adventure-works.com",
		"City" : "Elgin",
		"state_province" : "Illinois",
		"country_region" : "United States"
	},
	{
		"customer_id" : 112,
		"FirstName" : "David",
		"LastName" : "Bradley",
		"EmailAddress" : "david11@adventure-works.com",
		"City" : "Dallas",
		"state_province" : "Texas",
		"country_region" : "United States"
	},
	{
		"customer_id" : 113,
		"FirstName" : "Cornelius",
		"LastName" : "Brandon",
		"EmailAddress" : "cornelius0@adventure-works.com",
		"City" : "Fontana",
		"state_province" : "California",
		"country_region" : "United States"
	},
	{
		"customer_id" : 114,
		"FirstName" : "Richard",
		"LastName" : "Bready",
		"EmailAddress" : "richard1@adventure-works.com",
		"City" : "San Francisco",
		"state_province" : "California",
		"country_region" : "United States"
	},
	{
		"customer_id" : 115,
		"FirstName" : "Sara",
		"LastName" : "Breer",
		"EmailAddress" : "sara0@adventure-works.com",
		"City" : "Sparks",
		"state_province" : "Nevada",
		"country_region" : "United States"
	},
	{
		"customer_id" : 116,
		"FirstName" : "Ted",
		"LastName" : "Bremer",
		"EmailAddress" : "ted0@adventure-works.com",
		"City" : "Atlanta",
		"state_province" : "Georgia",
		"country_region" : "United States"
	},
	{
		"customer_id" : 117,
		"FirstName" : "Alan",
		"LastName" : "Brewer",
		"EmailAddress" : "alan1@adventure-works.com",
		"City" : "Suwanee",
		"state_province" : "Georgia",
		"country_region" : "United States"
	},
	{
		"customer_id" : 118,
		"FirstName" : "Walter",
		"LastName" : "Brian",
		"EmailAddress" : "walter0@adventure-works.com",
		"City" : "Toronto",
		"state_province" : "Ontario",
		"country_region" : "Canada"
	},
	{
		"customer_id" : 119,
		"FirstName" : "Christopher",
		"LastName" : "Bright",
		"EmailAddress" : "christopher2@adventure-works.com",
		"City" : "Pnot-Rouge",
		"state_province" : "Quebec",
		"country_region" : "Canada"
	},
	{
		"customer_id" : 120,
		"FirstName" : "Carol",
		"LastName" : "Brink",
		"EmailAddress" : "carol1@adventure-works.com",
		"City" : "Montreal",
		"state_province" : "Quebec",
		"country_region" : "Canada"
	},
	{
		"customer_id" : 121,
		"FirstName" : "David",
		"LastName" : "Brink",
		"EmailAddress" : "david12@adventure-works.com",
		"City" : "Saint Ouen",
		"state_province" : "Loir et Cher",
		"country_region" : "France"
	},
	{
		"customer_id" : 122,
		"FirstName" : "John",
		"LastName" : "Brooks",
		"EmailAddress" : "john12@adventure-works.com",
		"City" : "Berlin",
		"state_province" : "Hessen",
		"country_region" : "Germany"
	},
	{
		"customer_id" : 123,
		"FirstName" : "Willie",
		"LastName" : "Brooks",
		"EmailAddress" : "willie0@adventure-works.com",
		"City" : "North Ryde",
		"state_province" : "New South Wales",
		"country_region" : "Australia"
	},
	{
		"customer_id" : 124,
		"FirstName" : "Carolee",
		"LastName" : "Brown",
		"EmailAddress" : "carolee0@adventure-works.com",
		"City" : "W. York",
		"state_province" : "England",
		"country_region" : "United Kingdom"
	},
	{
		"customer_id" : 125,
		"FirstName" : "Jo",
		"LastName" : "Brown",
		"EmailAddress" : "jo2@adventure-works.com",
		"City" : "Stamford",
		"state_province" : "Connecticut",
		"country_region" : "United States"
	},
	{
		"customer_id" : 126,
		"FirstName" : "Robert",
		"LastName" : "Brown",
		"EmailAddress" : "robert5@adventure-works.com",
		"City" : "Endicott",
		"state_province" : "New York",
		"country_region" : "United States"
	},
	{
		"customer_id" : 127,
		"FirstName" : "Kevin",
		"LastName" : "Browne",
		"EmailAddress" : "kevin3@adventure-works.com",
		"City" : "Redmond",
		"state_province" : "Washington",
		"country_region" : "United States"
	},
	{
		"customer_id" : 128,
		"FirstName" : "Mary",
		"LastName" : "Browning",
		"EmailAddress" : "mary5@adventure-works.com",
		"City" : "Wenatchee",
		"state_province" : "Washington",
		"country_region" : "United States"
	},
	{
		"customer_id" : 129,
		"FirstName" : "Dave",
		"LastName" : "Browning",
		"EmailAddress" : "dave0@adventure-works.com",
		"City" : "Wood Dale",
		"state_province" : "Illinois",
		"country_region" : "United States"
	},
	{
		"customer_id" : 130,
		"FirstName" : "Bridget",
		"LastName" : "Browqett",
		"EmailAddress" : "bridget0@adventure-works.com",
		"City" : "Dallas",
		"state_province" : "Texas",
		"country_region" : "United States"
	},
	{
		"customer_id" : 130,
		"FirstName" : "Bridget",
		"LastName" : "Browqett",
		"EmailAddress" : "bridget0@adventure-works.com",
		"City" : "Dallas",
		"state_province" : "Texas",
		"country_region" : "United States"
	},
	{
		"customer_id" : 131,
		"FirstName" : "Eric",
		"LastName" : "Brumfield",
		"EmailAddress" : "eric3@adventure-works.com",
		"City" : "El Segundo",
		"state_province" : "California",
		"country_region" : "United States"
	},
	{
		"customer_id" : 132,
		"FirstName" : "Dick",
		"LastName" : "Brummer",
		"EmailAddress" : "dick0@adventure-works.com",
		"City" : "Westminster",
		"state_province" : "Colorado",
		"country_region" : "United States"
	},
	{
		"customer_id" : 133,
		"FirstName" : "Michael",
		"LastName" : "Brundage",
		"EmailAddress" : "michael13@adventure-works.com",
		"City" : "Modesto",
		"state_province" : "California",
		"country_region" : "United States"
	},
	{
		"customer_id" : 134,
		"FirstName" : "Shirley",
		"LastName" : "Bruner",
		"EmailAddress" : "shirley0@adventure-works.com",
		"City" : "Millington",
		"state_province" : "Tennessee",
		"country_region" : "United States"
	},
	{
		"customer_id" : 135,
		"FirstName" : "June",
		"LastName" : "Brunner",
		"EmailAddress" : "june0@adventure-works.com",
		"City" : "Memphis",
		"state_province" : "Tennessee",
		"country_region" : "United States"
	},
	{
		"customer_id" : 136,
		"FirstName" : "Dirk",
		"LastName" : "Bruno",
		"EmailAddress" : "dirk0@adventure-works.com",
		"City" : "Calgary",
		"state_province" : "Alberta",
		"country_region" : "Canada"
	},
	{
		"customer_id" : 137,
		"FirstName" : "Nancy",
		"LastName" : "Buchanan",
		"EmailAddress" : "nancy1@adventure-works.com",
		"City" : "Calgary",
		"state_province" : "Alberta",
		"country_region" : "Canada"
	},
	{
		"customer_id" : 138,
		"FirstName" : "Janaina Barreiro Gambaro",
		"LastName" : "Bueno",
		"EmailAddress" : "janainabarreirogambaro0@adventure-works.com",
		"City" : "Vancouver",
		"state_province" : "British Columbia",
		"country_region" : "Canada"
	},
	{
		"customer_id" : 139,
		"FirstName" : "Edward",
		"LastName" : "Buensalido",
		"EmailAddress" : "edward0@adventure-works.com",
		"City" : "Colombes",
		"state_province" : "Hauts de Seine",
		"country_region" : "France"
	},
	{
		"customer_id" : 140,
		"FirstName" : "Megan",
		"LastName" : "Burke",
		"EmailAddress" : "megan0@adventure-works.com",
		"City" : "Bonn",
		"state_province" : "Hamburg",
		"country_region" : "Germany"
	},
	{
		"customer_id" : 141,
		"FirstName" : "Ingrid",
		"LastName" : "Burkhardt",
		"EmailAddress" : "ingrid0@adventure-works.com",
		"City" : "Lavender Bay",
		"state_province" : "New South Wales",
		"country_region" : "Australia"
	},
	{
		"customer_id" : 142,
		"FirstName" : "Karren",
		"LastName" : "Burkhardt",
		"EmailAddress" : "karren0@adventure-works.com",
		"City" : "Scotland",
		"state_province" : "England",
		"country_region" : "United Kingdom"
	},
	{
		"customer_id" : 143,
		"FirstName" : "Ovidiu",
		"LastName" : "Burlacu",
		"EmailAddress" : "ovidiu1@adventure-works.com",
		"City" : "East Haven",
		"state_province" : "Connecticut",
		"country_region" : "United States"
	},
	{
		"customer_id" : 144,
		"FirstName" : "Dana",
		"LastName" : "Burnell",
		"EmailAddress" : "dana0@adventure-works.com",
		"City" : "New York",
		"state_province" : "New York",
		"country_region" : "United States"
	},
	{
		"customer_id" : 145,
		"FirstName" : "Timothy",
		"LastName" : "Burnett",
		"EmailAddress" : "timothy0@adventure-works.com",
		"City" : "Redmond",
		"state_province" : "Washington",
		"country_region" : "United States"
	},
	{
		"customer_id" : 146,
		"FirstName" : "Stephen",
		"LastName" : "Burton",
		"EmailAddress" : "stephen2@adventure-works.com",
		"City" : "Seattle",
		"state_province" : "Washington",
		"country_region" : "United States"
	},
	{
		"customer_id" : 147,
		"FirstName" : "Deanna",
		"LastName" : "Buskirk",
		"EmailAddress" : "deanna0@adventure-works.com",
		"City" : "Chicago",
		"state_province" : "Illinois",
		"country_region" : "United States"
	},
	{
		"customer_id" : 148,
		"FirstName" : "Jared",
		"LastName" : "Bustamante",
		"EmailAddress" : "jared0@adventure-works.com",
		"City" : "Carol Stream",
		"state_province" : "Illinois",
		"country_region" : "United States"
	},
	{
		"customer_id" : 149,
		"FirstName" : "Richard",
		"LastName" : "Byham",
		"EmailAddress" : "richard2@adventure-works.com",
		"City" : "Westminster",
		"state_province" : "Colorado",
		"country_region" : "United States"
	},
	{
		"customer_id" : 150,
		"FirstName" : "David",
		"LastName" : "Byrnes",
		"EmailAddress" : "david13@adventure-works.com",
		"City" : "Stockton",
		"state_province" : "California",
		"country_region" : "United States"
	},
	{
		"customer_id" : 151,
		"FirstName" : "Ryan",
		"LastName" : "Calafato",
		"EmailAddress" : "ryan1@adventure-works.com",
		"City" : "Culver City",
		"state_province" : "California",
		"country_region" : "United States"
	},
	{
		"customer_id" : 152,
		"FirstName" : "Sylvia",
		"LastName" : "Caldwell",
		"EmailAddress" : "sylvia0@adventure-works.com",
		"City" : "Clarkston",
		"state_province" : "Georgia",
		"country_region" : "United States"
	},
	{
		"customer_id" : 153,
		"FirstName" : "Mari",
		"LastName" : "Caldwell",
		"EmailAddress" : "mari0@adventure-works.com",
		"City" : "Clearwater",
		"state_province" : "Florida",
		"country_region" : "United States"
	},
	{
		"customer_id" : 154,
		"FirstName" : "Barbara",
		"LastName" : "Calone",
		"EmailAddress" : "barbara2@adventure-works.com",
		"City" : "Vancouver",
		"state_province" : "British Columbia",
		"country_region" : "Canada"
	},
	{
		"customer_id" : 155,
		"FirstName" : "Lindsey",
		"LastName" : "Camacho",
		"EmailAddress" : "lindsey0@adventure-works.com",
		"City" : "Toronto",
		"state_province" : "Ontario",
		"country_region" : "Canada"
	},
	{
		"customer_id" : 156,
		"FirstName" : "Gustavo",
		"LastName" : "Camargo",
		"EmailAddress" : "gustavo1@adventure-works.com",
		"City" : "Montreal",
		"state_province" : "Quebec",
		"country_region" : "Canada"
	},
	{
		"customer_id" : 157,
		"FirstName" : "DeeDee",
		"LastName" : "Cameron",
		"EmailAddress" : "deedee0@adventure-works.com",
		"City" : "Paris",
		"state_province" : "Seine (Paris)",
		"country_region" : "France"
	},
	{
		"customer_id" : 158,
		"FirstName" : "Deborah",
		"LastName" : "Lee",
		"EmailAddress" : "deborah1@adventure-works.com",
		"City" : "Bonn",
		"state_province" : "Nordrhein-Westfalen",
		"country_region" : "Germany"
	},
	{
		"customer_id" : 159,
		"FirstName" : "Joan",
		"LastName" : "Campbell",
		"EmailAddress" : "joan0@adventure-works.com",
		"City" : "North Ryde",
		"state_province" : "New South Wales",
		"country_region" : "Australia"
	},
	{
		"customer_id" : 160,
		"FirstName" : "David",
		"LastName" : "Campbell",
		"EmailAddress" : "david14@adventure-works.com",
		"City" : "Oxon",
		"state_province" : "England",
		"country_region" : "United Kingdom"
	},
	{
		"customer_id" : 161,
		"FirstName" : "Henry",
		"LastName" : "Campen",
		"EmailAddress" : "henry0@adventure-works.com",
		"City" : "Fort Wayne",
		"state_province" : "Indiana",
		"country_region" : "United States"
	},
	{
		"customer_id" : 162,
		"FirstName" : "Chris",
		"LastName" : "Cannon",
		"EmailAddress" : "chris5@adventure-works.com",
		"City" : "Warwick",
		"state_province" : "Rhode Island",
		"country_region" : "United States"
	},
	{
		"customer_id" : 163,
		"FirstName" : "Joseph",
		"LastName" : "Cantoni",
		"EmailAddress" : "joseph0@adventure-works.com",
		"City" : "Klamath Falls",
		"state_province" : "Oregon",
		"country_region" : "United States"
	},
	{
		"customer_id" : 164,
		"FirstName" : "Suzana De Abreu",
		"LastName" : "Canuto",
		"EmailAddress" : "suzanadeabreu0@adventure-works.com",
		"City" : "Troutdale",
		"state_province" : "Oregon",
		"country_region" : "United States"
	},
	{
		"customer_id" : 165,
		"FirstName" : "Jun",
		"LastName" : "Cao",
		"EmailAddress" : "jun1@adventure-works.com",
		"City" : "Dallas",
		"state_province" : "Texas",
		"country_region" : "United States"
	},
	{
		"customer_id" : 166,
		"FirstName" : "Johnny",
		"LastName" : "Caprio",
		"EmailAddress" : "johnny0@adventure-works.com",
		"City" : "Garland",
		"state_province" : "Texas",
		"country_region" : "United States"
	},
	{
		"customer_id" : 167,
		"FirstName" : "Richard",
		"LastName" : "Carey",
		"EmailAddress" : "richard3@adventure-works.com",
		"City" : "Carson",
		"state_province" : "California",
		"country_region" : "United States"
	},
	{
		"customer_id" : 168,
		"FirstName" : "Carlton",
		"LastName" : "Carlisle",
		"EmailAddress" : "carlton0@adventure-works.com",
		"City" : "Bell Gardens",
		"state_province" : "California",
		"country_region" : "United States"
	},
	{
		"customer_id" : 169,
		"FirstName" : "Ty Loren",
		"LastName" : "Carlson",
		"EmailAddress" : "tyloren0@adventure-works.com",
		"City" : "Fernley",
		"state_province" : "Nevada",
		"country_region" : "United States"
	},
	{
		"customer_id" : 170,
		"FirstName" : "Jane",
		"LastName" : "Carmichael",
		"EmailAddress" : "jane0@adventure-works.com",
		"City" : "Memphis",
		"state_province" : "Tennessee",
		"country_region" : "United States"
	},
	{
		"customer_id" : 171,
		"FirstName" : "Jovita",
		"LastName" : "Carmody",
		"EmailAddress" : "jovita0@adventure-works.com",
		"City" : "Mcdonough",
		"state_province" : "Georgia",
		"country_region" : "United States"
	},
	{
		"customer_id" : 172,
		"FirstName" : "Steve",
		"LastName" : "Carnes",
		"EmailAddress" : "steve1@adventure-works.com",
		"City" : "Richmond",
		"state_province" : "British Columbia",
		"country_region" : "Canada"
	},
	{
		"customer_id" : 173,
		"FirstName" : "Fernando",
		"LastName" : "Caro",
		"EmailAddress" : "fernando0@adventure-works.com",
		"City" : "Vancouver",
		"state_province" : "British Columbia",
		"country_region" : "Canada"
	},
	{
		"customer_id" : 174,
		"FirstName" : "Rob",
		"LastName" : "Caron",
		"EmailAddress" : "rob2@adventure-works.com",
		"City" : "Surrey",
		"state_province" : "British Columbia",
		"country_region" : "Canada"
	},
	{
		"customer_id" : 175,
		"FirstName" : "Andy",
		"LastName" : "Carothers",
		"EmailAddress" : "andy1@adventure-works.com",
		"City" : "Orleans",
		"state_province" : "Loiret",
		"country_region" : "France"
	},
	{
		"customer_id" : 176,
		"FirstName" : "Donna",
		"LastName" : "Carreras",
		"EmailAddress" : "donna0@adventure-works.com",
		"City" : "Münster",
		"state_province" : "Saarland",
		"country_region" : "Germany"
	},
	{
		"customer_id" : 177,
		"FirstName" : "Rosmarie",
		"LastName" : "Carroll",
		"EmailAddress" : "rosmarie0@adventure-works.com",
		"City" : "Hawthorne",
		"state_province" : "Queensland",
		"country_region" : "Australia"
	},
	{
		"customer_id" : 178,
		"FirstName" : "Matthew",
		"LastName" : "Carroll",
		"EmailAddress" : "matthew0@adventure-works.com",
		"City" : "W. York",
		"state_province" : "England",
		"country_region" : "United Kingdom"
	},
	{
		"customer_id" : 179,
		"FirstName" : "Joseph",
		"LastName" : "Castellucio",
		"EmailAddress" : "joseph1@adventure-works.com",
		"City" : "Mentor",
		"state_province" : "Ohio",
		"country_region" : "United States"
	},
	{
		"customer_id" : 180,
		"FirstName" : "Pamela",
		"LastName" : "Carlson",
		"EmailAddress" : "pamela1@adventure-works.com",
		"City" : "Pontiac",
		"state_province" : "Michigan",
		"country_region" : "United States"
	},
	{
		"customer_id" : 181,
		"FirstName" : "Raul",
		"LastName" : "Casts",
		"EmailAddress" : "raul0@adventure-works.com",
		"City" : "Clackamas",
		"state_province" : "Oregon",
		"country_region" : "United States"
	},
	{
		"customer_id" : 182,
		"FirstName" : "Elizabeth",
		"LastName" : "Catalano",
		"EmailAddress" : "elizabeth1@adventure-works.com",
		"City" : "Milwaukie",
		"state_province" : "Oregon",
		"country_region" : "United States"
	},
	{
		"customer_id" : 183,
		"FirstName" : "Matthew",
		"LastName" : "Cavallari",
		"EmailAddress" : "matthew1@adventure-works.com",
		"City" : "Chicago",
		"state_province" : "Illinois",
		"country_region" : "United States"
	},
	{
		"customer_id" : 184,
		"FirstName" : "Brigid",
		"LastName" : "Cavendish",
		"EmailAddress" : "brigid0@adventure-works.com",
		"City" : "Carrollton",
		"state_province" : "Texas",
		"country_region" : "United States"
	},
	{
		"customer_id" : 185,
		"FirstName" : "Andrew",
		"LastName" : "Cencini",
		"EmailAddress" : "andrew2@adventure-works.com",
		"City" : "San Jose",
		"state_province" : "California",
		"country_region" : "United States"
	},
	{
		"customer_id" : 186,
		"FirstName" : "Stacey",
		"LastName" : "Cereghino",
		"EmailAddress" : "stacey0@adventure-works.com",
		"City" : "Santa Fe",
		"state_province" : "New Mexico",
		"country_region" : "United States"
	},
	{
		"customer_id" : 187,
		"FirstName" : "Baris",
		"LastName" : "Cetinok",
		"EmailAddress" : "baris1@adventure-works.com",
		"City" : "Cerritos",
		"state_province" : "California",
		"country_region" : "United States"
	},
	{
		"customer_id" : 188,
		"FirstName" : "Sean",
		"LastName" : "Chai",
		"EmailAddress" : "sean3@adventure-works.com",
		"City" : "Miami",
		"state_province" : "Florida",
		"country_region" : "United States"
	},
	{
		"customer_id" : 189,
		"FirstName" : "Pat",
		"LastName" : "Chambers",
		"EmailAddress" : "pat1@adventure-works.com",
		"City" : "Mobile",
		"state_province" : "Alabama",
		"country_region" : "United States"
	},
	{
		"customer_id" : 190,
		"FirstName" : "Forrest",
		"LastName" : "Chandler",
		"EmailAddress" : "forrest0@adventure-works.com",
		"City" : "Calgary",
		"state_province" : "Alberta",
		"country_region" : "Canada"
	},
	{
		"customer_id" : 191,
		"FirstName" : "Lee",
		"LastName" : "Chapla",
		"EmailAddress" : "lee0@adventure-works.com",
		"City" : "Toronto",
		"state_province" : "Ontario",
		"country_region" : "Canada"
	},
	{
		"customer_id" : 192,
		"FirstName" : "Greg",
		"LastName" : "Chapman",
		"EmailAddress" : "greg1@adventure-works.com",
		"City" : "Toronto",
		"state_province" : "Ontario",
		"country_region" : "Canada"
	},
	{
		"customer_id" : 193,
		"FirstName" : "Neil",
		"LastName" : "Charney",
		"EmailAddress" : "neil0@adventure-works.com",
		"City" : "Colomiers",
		"state_province" : "Garonne (Haute)",
		"country_region" : "France"
	},
	{
		"customer_id" : 194,
		"FirstName" : "Hao",
		"LastName" : "Chen",
		"EmailAddress" : "hao1@adventure-works.com",
		"City" : "München",
		"state_province" : "Hamburg",
		"country_region" : "Germany"
	},
	{
		"customer_id" : 195,
		"FirstName" : "John",
		"LastName" : "Chen",
		"EmailAddress" : "john13@adventure-works.com",
		"City" : "North Sydney",
		"state_province" : "New South Wales",
		"country_region" : "Australia"
	},
	{
		"customer_id" : 196,
		"FirstName" : "Pei",
		"LastName" : "Chow",
		"EmailAddress" : "pei0@adventure-works.com",
		"City" : "Milton Keynes",
		"state_province" : "England",
		"country_region" : "United Kingdom"
	}
]
